connect_four/board.py
connect_four/game.py
connect_four/main.py
connect_four/assets/icon.png
connect_four/assets/nunito.ttf
connect_four_ai_demo-0.1.0.dist-info/METADATA
connect_four_ai_demo-0.1.0.dist-info/WHEEL
connect_four_ai_demo-0.1.0.dist-info/entry_points.txt
connect_four_ai_demo-0.1.0.dist-info/RECORD
