Metadata-Version: 2.4
Name: connect-four-ai-demo
Version: 0.1.0
Summary: A Pygame implementation of Connect Four against an AI opponent, using the `connect-four-ai` library.
Project-URL: Homepage, https://github.com/benjaminrall/connect-four-ai
Author-email: Benjamin Rall <benr2508@aol.com>
Classifier: License :: OSI Approved :: MIT License
Classifier: Programming Language :: Python :: 3
Requires-Python: >=3.13
Requires-Dist: connect-four-ai>=0.1.2
Requires-Dist: pygame>=2.6.1
